balderich/__init__.py
balderich/client.py
balderich/models/__init__.py
balderich/models/contest.py
balderich/models/problem.py
balderich/models/resource.py
balderich/models/team.py
balderich/models/user.py
balderich/utils/__init__.py
balderich/utils/code.py
balderich/utils/exceptions.py
balderich-1.3.dist-info/LICENSE
balderich-1.3.dist-info/METADATA
balderich-1.3.dist-info/WHEEL
balderich-1.3.dist-info/top_level.txt
balderich-1.3.dist-info/RECORD
