Metadata-Version: 2.1
Name: balderich
Version: 1.3
Summary: A Python library for the NSSCTF Balderich API
Home-page: https://github.com/NSSCTF/balderich-py
Author: NSSCTF
Classifier: Intended Audience :: Developers
Classifier: License :: OSI Approved :: MIT License
Classifier: Natural Language :: English
Classifier: Programming Language :: Python :: 3.8
Classifier: Programming Language :: Python :: 3.9
Classifier: Programming Language :: Python :: 3.10
Requires-Python: >=3.8
License-File: LICENSE
